{"code": 200, "total_asks": 50, "asks": [{"order_index": 8725724407127992, "order_id": "8725724407127992", "owner_account_index": 317087, "initial_base_amount": "345.88", "remaining_base_amount": "345.88", "price": "3.9813", "order_expiry": 1775212286590, "transaction_time": 0}, {"order_index": 8725724407127930, "order_id": "8725724407127930", "owner_account_index": 317087, "initial_base_amount": "530.79", "remaining_base_amount": "530.79", "price": "3.9814", "order_expiry": 1775212259994, "transaction_time": 0}, {"order_index": 8725724407127993, "order_id": "8725724407127993", "owner_account_index": 277239, "initial_base_amount": "113.87", "remaining_base_amount": "113.87", "price": "3.9819", "order_expiry": 1775212286664, "transaction_time": 0}, {"order_index": 8725724407127858, "order_id": "8725724407127858", "owner_account_index": 314236, "initial_base_amount": "107.63", "remaining_base_amount": "107.63", "price": "3.9833", "order_expiry": 1775212231193, "transaction_time": 0}, {"order_index": 8725724407023388, "order_id": "8725724407023388", "owner_account_index": 281474976710654, "initial_base_amount": "988.20", "remaining_base_amount": "988.20", "price": "3.9840", "order_expiry": 1775347854728, "transaction_time": 0}, {"order_index": 8725724407127994, "order_id": "8725724407127994", "owner_account_index": 366058, "initial_base_amount": "2315.45", "remaining_base_amount": "2315.45", "price": "3.9847", "order_expiry": 1772794886693, "transaction_time": 0}, {"order_index": 8725724407127931, "order_id": "8725724407127931", "owner_account_index": 317087, "initial_base_amount": "3585.80", "remaining_base_amount": "3585.80", "price": "3.9858", "order_expiry": 1775212260018, "transaction_time": 0}, {"order_index": 8725724407127784, "order_id": "8725724407127784", "owner_account_index": 314236, "initial_base_amount": "438.64", "remaining_base_amount": "438.64", "price": "3.9863", "order_expiry": 1775212215384, "transaction_time": 0}, {"order_index": 8725724407023407, "order_id": "8725724407023407", "owner_account_index": 281474976710654, "initial_base_amount": "1234.93", "remaining_base_amount": "1234.86", "price": "3.9863", "order_expiry": 1775347855466, "transaction_time": 0}, {"order_index": 8725724407037257, "order_id": "8725724407037257", "owner_account_index": 281474976710654, "initial_base_amount": "1541.11", "remaining_base_amount": "1541.10", "price": "3.9873", "order_expiry": 1775353052967, "transaction_time": 0}, {"order_index": 8725724407127695, "order_id": "8725724407127695", "owner_account_index": 714874, "initial_base_amount": "225.97", "remaining_base_amount": "225.97", "price": "3.9874", "order_expiry": 1775212188322, "transaction_time": 0}, {"order_index": 8725724407127665, "order_id": "8725724407127665", "owner_account_index": 714874, "initial_base_amount": "225.92", "remaining_base_amount": "225.92", "price": "3.9879", "order_expiry": 1775212179302, "transaction_time": 0}, {"order_index": 8725724407127782, "order_id": "8725724407127782", "owner_account_index": 366058, "initial_base_amount": "2315.90", "remaining_base_amount": "2315.90", "price": "3.9885", "order_expiry": 1772794814955, "transaction_time": 0}, {"order_index": 8725724407127861, "order_id": "8725724407127861", "owner_account_index": 314236, "initial_base_amount": "2174.39", "remaining_base_amount": "2174.39", "price": "3.9925", "order_expiry": 1775212231287, "transaction_time": 0}, {"order_index": 8725724407127563, "order_id": "8725724407127563", "owner_account_index": 30323, "initial_base_amount": "9722.00", "remaining_base_amount": "9722.00", "price": "3.9998", "order_expiry": 1775212165910, "transaction_time": 0}, {"order_index": 8725724407124319, "order_id": "8725724407124319", "owner_account_index": 281474976626175, "initial_base_amount": "24374.13", "remaining_base_amount": "24374.13", "price": "4.0003", "order_expiry": 1775210660827, "transaction_time": 0}, {"order_index": 8725724407127854, "order_id": "8725724407127854", "owner_account_index": 317087, "initial_base_amount": "13269.69", "remaining_base_amount": "13269.69", "price": "4.0028", "order_expiry": 1775212231138, "transaction_time": 0}, {"order_index": 8725724407127649, "order_id": "8725724407127649", "owner_account_index": 714874, "initial_base_amount": "602.63", "remaining_base_amount": "602.63", "price": "4.0128", "order_expiry": 1775212176121, "transaction_time": 0}, {"order_index": 8725724407127664, "order_id": "8725724407127664", "owner_account_index": 714874, "initial_base_amount": "602.46", "remaining_base_amount": "602.46", "price": "4.0154", "order_expiry": 1775212179299, "transaction_time": 0}, {"order_index": 8725724407127553, "order_id": "8725724407127553", "owner_account_index": 314236, "initial_base_amount": "8291.62", "remaining_base_amount": "8291.62", "price": "4.0213", "order_expiry": 1775212165592, "transaction_time": 0}, {"order_index": 8725724405859754, "order_id": "8725724405859754", "owner_account_index": 281474976710654, "initial_base_amount": "3892.47", "remaining_base_amount": "3892.47", "price": "4.0226", "order_expiry": 1775064134576, "transaction_time": 0}, {"order_index": 8725724405859755, "order_id": "8725724405859755", "owner_account_index": 281474976710654, "initial_base_amount": "5543.46", "remaining_base_amount": "5543.46", "price": "4.0266", "order_expiry": 1775064134577, "transaction_time": 0}, {"order_index": 8725724405859756, "order_id": "8725724405859756", "owner_account_index": 281474976710654, "initial_base_amount": "5456.04", "remaining_base_amount": "5456.04", "price": "4.0305", "order_expiry": 1775064134577, "transaction_time": 0}, {"order_index": 8725724407127590, "order_id": "8725724407127590", "owner_account_index": 281474976626175, "initial_base_amount": "13923.47", "remaining_base_amount": "13923.47", "price": "4.0316", "order_expiry": 1775212168064, "transaction_time": 0}, {"order_index": 8725724405859758, "order_id": "8725724405859758", "owner_account_index": 281474976710654, "initial_base_amount": "4882.91", "remaining_base_amount": "4882.91", "price": "4.0345", "order_expiry": 1775064134578, "transaction_time": 0}, {"order_index": 8725724405859757, "order_id": "8725724405859757", "owner_account_index": 281474976710654, "initial_base_amount": "4231.95", "remaining_base_amount": "4231.95", "price": "4.0385", "order_expiry": 1775064134578, "transaction_time": 0}, {"order_index": 8725724405859759, "order_id": "8725724405859759", "owner_account_index": 281474976710654, "initial_base_amount": "3628.42", "remaining_base_amount": "3628.42", "price": "4.0425", "order_expiry": 1775064134579, "transaction_time": 0}, {"order_index": 8725724405859760, "order_id": "8725724405859760", "owner_account_index": 281474976710654, "initial_base_amount": "3104.25", "remaining_base_amount": "3104.25", "price": "4.0465", "order_expiry": 1775064134579, "transaction_time": 0}, {"order_index": 8725724406928665, "order_id": "8725724406928665", "owner_account_index": 213915, "initial_base_amount": "176.09", "remaining_base_amount": "176.09", "price": "4.0479", "order_expiry": 1775145724591, "transaction_time": 0}, {"order_index": 8725724407126727, "order_id": "8725724407126727", "owner_account_index": 714874, "initial_base_amount": "65.25", "remaining_base_amount": "65.25", "price": "4.0498", "order_expiry": 1775211695345, "transaction_time": 0}, {"order_index": 8725724405859761, "order_id": "8725724405859761", "owner_account_index": 281474976710654, "initial_base_amount": "2660.22", "remaining_base_amount": "2660.22", "price": "4.0505", "order_expiry": 1775064134580, "transaction_time": 0}, {"order_index": 8725724405859762, "order_id": "8725724405859762", "owner_account_index": 281474976710654, "initial_base_amount": "2287.49", "remaining_base_amount": "2287.49", "price": "4.0544", "order_expiry": 1775064134580, "transaction_time": 0}, {"order_index": 8725724405859763, "order_id": "8725724405859763", "owner_account_index": 281474976710654, "initial_base_amount": "1975.18", "remaining_base_amount": "1975.18", "price": "4.0584", "order_expiry": 1775064134581, "transaction_time": 0}, {"order_index": 8725724407124279, "order_id": "8725724407124279", "owner_account_index": 30323, "initial_base_amount": "9545.00", "remaining_base_amount": "9545.00", "price": "4.0740", "order_expiry": 1775210647884, "transaction_time": 0}, {"order_index": 8725724406928728, "order_id": "8725724406928728", "owner_account_index": 213915, "initial_base_amount": "228.04", "remaining_base_amount": "228.04", "price": "4.1170", "order_expiry": 1775145739591, "transaction_time": 0}, {"order_index": 8725724404448306, "order_id": "8725724404448306", "owner_account_index": 98666, "initial_base_amount": "10.92", "remaining_base_amount": "10.92", "price": "4.1246", "order_expiry": 1774536134046, "transaction_time": 0}, {"order_index": 8725724405804076, "order_id": "8725724405804076", "owner_account_index": 281474976623503, "initial_base_amount": "14.87", "remaining_base_amount": "14.87", "price": "4.1400", "order_expiry": 1774884550826, "transaction_time": 0}, {"order_index": 8725724407113467, "order_id": "8725724407113467", "owner_account_index": 30323, "initial_base_amount": "9365.00", "remaining_base_amount": "9365.00", "price": "4.1524", "order_expiry": 1775207613813, "transaction_time": 0}, {"order_index": 8725724406668827, "order_id": "8725724406668827", "owner_account_index": 383397, "initial_base_amount": "2.57", "remaining_base_amount": "2.57", "price": "4.2806", "order_expiry": 1775072167698, "transaction_time": 0}, {"order_index": 8725724396225174, "order_id": "8725724396225174", "owner_account_index": 383397, "initial_base_amount": "2.50", "remaining_base_amount": "2.50", "price": "4.3552", "order_expiry": 1772795335020, "transaction_time": 0}, {"order_index": 8725724396225691, "order_id": "8725724396225691", "owner_account_index": 383397, "initial_base_amount": "3.00", "remaining_base_amount": "3.00", "price": "4.4608", "order_expiry": 1772795395219, "transaction_time": 0}, {"order_index": 8725724405414511, "order_id": "8725724405414511", "owner_account_index": 248858, "initial_base_amount": "200.00", "remaining_base_amount": "200.00", "price": "4.5000", "order_expiry": 1774785710119, "transaction_time": 0}, {"order_index": 8725724407127912, "order_id": "8725724407127912", "owner_account_index": 675262, "initial_base_amount": "28.89", "remaining_base_amount": "28.89", "price": "4.5370", "order_expiry": 1775212254641, "transaction_time": 0}, {"order_index": 8725724398816881, "order_id": "8725724398816881", "owner_account_index": 383397, "initial_base_amount": "2.30", "remaining_base_amount": "2.30", "price": "4.5663", "order_expiry": 1773239834278, "transaction_time": 0}, {"order_index": 8725724405414512, "order_id": "8725724405414512", "owner_account_index": 248858, "initial_base_amount": "200.00", "remaining_base_amount": "200.00", "price": "4.6315", "order_expiry": 1774785710119, "transaction_time": 0}, {"order_index": 8725724396225217, "order_id": "8725724396225217", "owner_account_index": 383397, "initial_base_amount": "2.20", "remaining_base_amount": "2.20", "price": "4.6828", "order_expiry": 1772795338204, "transaction_time": 0}, {"order_index": 8725724396225434, "order_id": "8725724396225434", "owner_account_index": 383397, "initial_base_amount": "3.00", "remaining_base_amount": "3.00", "price": "4.7613", "order_expiry": 1772795368644, "transaction_time": 0}, {"order_index": 8725724405414513, "order_id": "8725724405414513", "owner_account_index": 248858, "initial_base_amount": "200.00", "remaining_base_amount": "200.00", "price": "4.7631", "order_expiry": 1774785710119, "transaction_time": 0}, {"order_index": 8725724396225713, "order_id": "8725724396225713", "owner_account_index": 383397, "initial_base_amount": "3.00", "remaining_base_amount": "3.00", "price": "4.8479", "order_expiry": 1772795397672, "transaction_time": 0}, {"order_index": 8725724398754037, "order_id": "8725724398754037", "owner_account_index": 36450, "initial_base_amount": "143.67", "remaining_base_amount": "143.67", "price": "4.8500", "order_expiry": 1773238792096, "transaction_time": 0}], "total_bids": 50, "bids": [{"order_index": 9007199124766432, "order_id": "9007199124766432", "owner_account_index": 317087, "initial_base_amount": "348.63", "remaining_base_amount": "348.63", "price": "3.9791", "order_expiry": 1775212286961, "transaction_time": 0}, {"order_index": 9007199124930447, "order_id": "9007199124930447", "owner_account_index": 281474976710654, "initial_base_amount": "2293.02", "remaining_base_amount": "891.01", "price": "3.9791", "order_expiry": 1775327292657, "transaction_time": 0}, {"order_index": 9007199124766433, "order_id": "9007199124766433", "owner_account_index": 277239, "initial_base_amount": "107.39", "remaining_base_amount": "107.39", "price": "3.9790", "order_expiry": 1775212286921, "transaction_time": 0}, {"order_index": 9007199124766436, "order_id": "9007199124766436", "owner_account_index": 30323, "initial_base_amount": "977.00", "remaining_base_amount": "977.00", "price": "3.9788", "order_expiry": 1775212286579, "transaction_time": 0}, {"order_index": 9007199124766438, "order_id": "9007199124766438", "owner_account_index": 281474976644066, "initial_base_amount": "438.21", "remaining_base_amount": "438.21", "price": "3.9787", "order_expiry": 1772879462791, "transaction_time": 0}, {"order_index": 9007199124766476, "order_id": "9007199124766476", "owner_account_index": 281474976649277, "initial_base_amount": "438.16", "remaining_base_amount": "438.16", "price": "3.9776", "order_expiry": 1772879463755, "transaction_time": 0}, {"order_index": 9007199124766427, "order_id": "9007199124766427", "owner_account_index": 366058, "initial_base_amount": "2316.29", "remaining_base_amount": "2316.29", "price": "3.9775", "order_expiry": 1772794889154, "transaction_time": 0}, {"order_index": 9007199124766595, "order_id": "9007199124766595", "owner_account_index": 317087, "initial_base_amount": "524.33", "remaining_base_amount": "524.33", "price": "3.9763", "order_expiry": 1775212229899, "transaction_time": 0}, {"order_index": 9007199124922233, "order_id": "9007199124922233", "owner_account_index": 281474976710654, "initial_base_amount": "1114.70", "remaining_base_amount": "1114.70", "price": "3.9751", "order_expiry": 1775329445908, "transaction_time": 0}, {"order_index": 9007199124766586, "order_id": "9007199124766586", "owner_account_index": 314236, "initial_base_amount": "107.97", "remaining_base_amount": "107.97", "price": "3.9749", "order_expiry": 1775212231153, "transaction_time": 0}, {"order_index": 9007199124766422, "order_id": "9007199124766422", "owner_account_index": 325824, "initial_base_amount": "2168.44", "remaining_base_amount": "2168.44", "price": "3.9745", "order_expiry": 1775212295218, "transaction_time": 0}, {"order_index": 9007199124929769, "order_id": "9007199124929769", "owner_account_index": 281474976710654, "initial_base_amount": "1891.62", "remaining_base_amount": "1391.14", "price": "3.9741", "order_expiry": 1775327435696, "transaction_time": 0}, {"order_index": 9007199124766584, "order_id": "9007199124766584", "owner_account_index": 314236, "initial_base_amount": "440.63", "remaining_base_amount": "440.63", "price": "3.9734", "order_expiry": 1775212231195, "transaction_time": 0}, {"order_index": 9007199124766665, "order_id": "9007199124766665", "owner_account_index": 317087, "initial_base_amount": "3495.53", "remaining_base_amount": "3495.53", "price": "3.9730", "order_expiry": 1775212215223, "transaction_time": 0}, {"order_index": 9007199124766434, "order_id": "9007199124766434", "owner_account_index": 366058, "initial_base_amount": "2316.04", "remaining_base_amount": "2316.04", "price": "3.9730", "order_expiry": 1772794886693, "transaction_time": 0}, {"order_index": 9007199124766725, "order_id": "9007199124766725", "owner_account_index": 714874, "initial_base_amount": "225.94", "remaining_base_amount": "225.94", "price": "3.9671", "order_expiry": 1775212200925, "transaction_time": 0}, {"order_index": 9007199124766505, "order_id": "9007199124766505", "owner_account_index": 714874, "initial_base_amount": "225.85", "remaining_base_amount": "225.85", "price": "3.9671", "order_expiry": 1775212259920, "transaction_time": 0}, {"order_index": 9007199124766581, "order_id": "9007199124766581", "owner_account_index": 314236, "initial_base_amount": "2123.88", "remaining_base_amount": "2123.88", "price": "3.9660", "order_expiry": 1775212231289, "transaction_time": 0}, {"order_index": 9007199124766828, "order_id": "9007199124766828", "owner_account_index": 30323, "initial_base_amount": "9821.00", "remaining_base_amount": "9821.00", "price": "3.9596", "order_expiry": 1775212171910, "transaction_time": 0}, {"order_index": 9007199124766585, "order_id": "9007199124766585", "owner_account_index": 317087, "initial_base_amount": "13368.59", "remaining_base_amount": "13368.59", "price": "3.9580", "order_expiry": 1775212231163, "transaction_time": 0}, {"order_index": 9007199124766862, "order_id": "9007199124766862", "owner_account_index": 281474976626175, "initial_base_amount": "24324.94", "remaining_base_amount": "24324.94", "price": "3.9552", "order_expiry": 1775212168059, "transaction_time": 0}, {"order_index": 9007199124766430, "order_id": "9007199124766430", "owner_account_index": 714874, "initial_base_amount": "602.37", "remaining_base_amount": "602.37", "price": "3.9436", "order_expiry": 1775212287529, "transaction_time": 0}, {"order_index": 9007199124766882, "order_id": "9007199124766882", "owner_account_index": 314236, "initial_base_amount": "8097.98", "remaining_base_amount": "8097.98", "price": "3.9402", "order_expiry": 1775212167685, "transaction_time": 0}, {"order_index": 9007199126072396, "order_id": "9007199126072396", "owner_account_index": 281474976710654, "initial_base_amount": "3779.00", "remaining_base_amount": "3779.00", "price": "3.9401", "order_expiry": 1775064134567, "transaction_time": 0}, {"order_index": 9007199124766784, "order_id": "9007199124766784", "owner_account_index": 714874, "initial_base_amount": "602.46", "remaining_base_amount": "602.46", "price": "3.9397", "order_expiry": 1775212179297, "transaction_time": 0}, {"order_index": 9007199126072397, "order_id": "9007199126072397", "owner_account_index": 281474976710654, "initial_base_amount": "5381.87", "remaining_base_amount": "5381.87", "price": "3.9361", "order_expiry": 1775064134568, "transaction_time": 0}, {"order_index": 9007199124766861, "order_id": "9007199124766861", "owner_account_index": 281474976626175, "initial_base_amount": "13923.47", "remaining_base_amount": "13923.47", "price": "3.9337", "order_expiry": 1775212168061, "transaction_time": 0}, {"order_index": 9007199126072395, "order_id": "9007199126072395", "owner_account_index": 281474976710654, "initial_base_amount": "5297.00", "remaining_base_amount": "5297.00", "price": "3.9321", "order_expiry": 1775064134568, "transaction_time": 0}, {"order_index": 9007199126072394, "order_id": "9007199126072394", "owner_account_index": 281474976710654, "initial_base_amount": "4740.57", "remaining_base_amount": "4740.57", "price": "3.9282", "order_expiry": 1775064134569, "transaction_time": 0}, {"order_index": 9007199126072393, "order_id": "9007199126072393", "owner_account_index": 281474976710654, "initial_base_amount": "4108.59", "remaining_base_amount": "4108.59", "price": "3.9242", "order_expiry": 1775064134569, "transaction_time": 0}, {"order_index": 9007199126072392, "order_id": "9007199126072392", "owner_account_index": 281474976710654, "initial_base_amount": "3522.66", "remaining_base_amount": "3522.66", "price": "3.9202", "order_expiry": 1775064134570, "transaction_time": 0}, {"order_index": 9007199124776829, "order_id": "9007199124776829", "owner_account_index": 47339, "initial_base_amount": "1000.00", "remaining_base_amount": "1000.00", "price": "3.9200", "order_expiry": 1775208970162, "transaction_time": 0}, {"order_index": 9007199126072391, "order_id": "9007199126072391", "owner_account_index": 281474976710654, "initial_base_amount": "3013.76", "remaining_base_amount": "3013.76", "price": "3.9162", "order_expiry": 1775064134570, "transaction_time": 0}, {"order_index": 9007199126072390, "order_id": "9007199126072390", "owner_account_index": 281474976710654, "initial_base_amount": "2582.68", "remaining_base_amount": "2582.68", "price": "3.9122", "order_expiry": 1775064134571, "transaction_time": 0}, {"order_index": 9007199126072389, "order_id": "9007199126072389", "owner_account_index": 281474976710654, "initial_base_amount": "2220.81", "remaining_base_amount": "2220.81", "price": "3.9083", "order_expiry": 1775064134571, "transaction_time": 0}, {"order_index": 9007199124766798, "order_id": "9007199124766798", "owner_account_index": 714874, "initial_base_amount": "65.28", "remaining_base_amount": "65.28", "price": "3.9047", "order_expiry": 1775212176119, "transaction_time": 0}, {"order_index": 9007199126072388, "order_id": "9007199126072388", "owner_account_index": 281474976710654, "initial_base_amount": "1917.61", "remaining_base_amount": "1917.61", "price": "3.9043", "order_expiry": 1775064134572, "transaction_time": 0}, {"order_index": 9007199124770479, "order_id": "9007199124770479", "owner_account_index": 30323, "initial_base_amount": "10037.00", "remaining_base_amount": "10037.00", "price": "3.8742", "order_expiry": 1775210647879, "transaction_time": 0}, {"order_index": 9007199125510490, "order_id": "9007199125510490", "owner_account_index": 47339, "initial_base_amount": "1000.00", "remaining_base_amount": "1000.00", "price": "3.8224", "order_expiry": 1775020017281, "transaction_time": 0}, {"order_index": 9007199124782498, "order_id": "9007199124782498", "owner_account_index": 30323, "initial_base_amount": "10356.00", "remaining_base_amount": "10356.00", "price": "3.7550", "order_expiry": 1775207607836, "transaction_time": 0}, {"order_index": 9007199126375414, "order_id": "9007199126375414", "owner_account_index": 334987, "initial_base_amount": "25.00", "remaining_base_amount": "25.00", "price": "3.7000", "order_expiry": 1774822991195, "transaction_time": 0}, {"order_index": 9007199126375378, "order_id": "9007199126375378", "owner_account_index": 334987, "initial_base_amount": "25.00", "remaining_base_amount": "25.00", "price": "3.6000", "order_expiry": 1774823002812, "transaction_time": 0}, {"order_index": 9007199127507050, "order_id": "9007199127507050", "owner_account_index": 1976, "initial_base_amount": "195.81", "remaining_base_amount": "195.81", "price": "3.5052", "order_expiry": 1774537099658, "transaction_time": 0}, {"order_index": 9007199129649674, "order_id": "9007199129649674", "owner_account_index": 383397, "initial_base_amount": "3.84", "remaining_base_amount": "3.84", "price": "3.5034", "order_expiry": 1774016668807, "transaction_time": 0}, {"order_index": 9007199127507049, "order_id": "9007199127507049", "owner_account_index": 1976, "initial_base_amount": "207.68", "remaining_base_amount": "207.68", "price": "3.4631", "order_expiry": 1774537099658, "transaction_time": 0}, {"order_index": 9007199130544772, "order_id": "9007199130544772", "owner_account_index": 383397, "initial_base_amount": "4.00", "remaining_base_amount": "4.00", "price": "3.4462", "order_expiry": 1773769917429, "transaction_time": 0}, {"order_index": 9007199127507048, "order_id": "9007199127507048", "owner_account_index": 1976, "initial_base_amount": "219.54", "remaining_base_amount": "219.54", "price": "3.4210", "order_expiry": 1774537099658, "transaction_time": 0}, {"order_index": 9007199129649655, "order_id": "9007199129649655", "owner_account_index": 383397, "initial_base_amount": "3.55", "remaining_base_amount": "3.55", "price": "3.3967", "order_expiry": 1774016677007, "transaction_time": 0}, {"order_index": 9007199127507047, "order_id": "9007199127507047", "owner_account_index": 1976, "initial_base_amount": "231.40", "remaining_base_amount": "231.40", "price": "3.3789", "order_expiry": 1774537099658, "transaction_time": 0}, {"order_index": 9007199129649691, "order_id": "9007199129649691", "owner_account_index": 383397, "initial_base_amount": "3.42", "remaining_base_amount": "3.42", "price": "3.3396", "order_expiry": 1774016659494, "transaction_time": 0}]}