{"code": 200, "total_asks": 50, "asks": [{"order_index": 19421773464791416, "order_id": "19421773464791416", "owner_account_index": 281474976649277, "initial_base_amount": "478.2", "remaining_base_amount": "478.2", "price": "1.95568", "order_expiry": 1772851413750, "transaction_time": 0}, {"order_index": 19421773464781792, "order_id": "19421773464781792", "owner_account_index": 281474976710654, "initial_base_amount": "1451.0", "remaining_base_amount": "1340.3", "price": "1.95584", "order_expiry": 1775353812308, "transaction_time": 0}, {"order_index": 19421773464791382, "order_id": "19421773464791382", "owner_account_index": 366058, "initial_base_amount": "1534.7", "remaining_base_amount": "1534.7", "price": "1.95609", "order_expiry": 1772766819342, "transaction_time": 0}, {"order_index": 19421773464791396, "order_id": "19421773464791396", "owner_account_index": 102394, "initial_base_amount": "317.6", "remaining_base_amount": "317.6", "price": "1.95627", "order_expiry": 1775184221360, "transaction_time": 0}, {"order_index": 19421773464781856, "order_id": "19421773464781856", "owner_account_index": 281474976710654, "initial_base_amount": "1712.4", "remaining_base_amount": "1677.5", "price": "1.95628", "order_expiry": 1775353821229, "transaction_time": 0}, {"order_index": 19421773464791453, "order_id": "19421773464791453", "owner_account_index": 68785, "initial_base_amount": "766.6", "remaining_base_amount": "766.6", "price": "1.95669", "order_expiry": 1775184243650, "transaction_time": 0}, {"order_index": 19421773464780916, "order_id": "19421773464780916", "owner_account_index": 281474976710654, "initial_base_amount": "3806.0", "remaining_base_amount": "2093.5", "price": "1.95677", "order_expiry": 1775353550524, "transaction_time": 0}, {"order_index": 19421773464791370, "order_id": "19421773464791370", "owner_account_index": 102394, "initial_base_amount": "319.6", "remaining_base_amount": "319.6", "price": "1.95740", "order_expiry": 1775184218270, "transaction_time": 0}, {"order_index": 19421773464791420, "order_id": "19421773464791420", "owner_account_index": 281474976648047, "initial_base_amount": "586.2", "remaining_base_amount": "586.2", "price": "1.95802", "order_expiry": 1772851414361, "transaction_time": 0}, {"order_index": 19421773464791371, "order_id": "19421773464791371", "owner_account_index": 102394, "initial_base_amount": "349.8", "remaining_base_amount": "349.8", "price": "1.95872", "order_expiry": 1775184218297, "transaction_time": 0}, {"order_index": 19421773464791384, "order_id": "19421773464791384", "owner_account_index": 102394, "initial_base_amount": "383.5", "remaining_base_amount": "383.5", "price": "1.96159", "order_expiry": 1775184219608, "transaction_time": 0}, {"order_index": 19421773464791331, "order_id": "19421773464791331", "owner_account_index": 102394, "initial_base_amount": "767.6", "remaining_base_amount": "767.6", "price": "1.96808", "order_expiry": 1775184194429, "transaction_time": 0}, {"order_index": 19421773464783054, "order_id": "19421773464783054", "owner_account_index": 281474976710654, "initial_base_amount": "3178.6", "remaining_base_amount": "3178.6", "price": "1.97042", "order_expiry": 1775354102851, "transaction_time": 0}, {"order_index": 19421773464783055, "order_id": "19421773464783055", "owner_account_index": 281474976710654, "initial_base_amount": "4526.7", "remaining_base_amount": "4526.7", "price": "1.97237", "order_expiry": 1775354102851, "transaction_time": 0}, {"order_index": 19421773463719266, "order_id": "19421773463719266", "owner_account_index": 281474976710654, "initial_base_amount": "8411.8", "remaining_base_amount": "4455.4", "price": "1.97433", "order_expiry": 1775064134580, "transaction_time": 0}, {"order_index": 19421773463719267, "order_id": "19421773463719267", "owner_account_index": 281474976710654, "initial_base_amount": "3987.3", "remaining_base_amount": "3987.3", "price": "1.97628", "order_expiry": 1775064134580, "transaction_time": 0}, {"order_index": 19421773463719268, "order_id": "19421773463719268", "owner_account_index": 281474976710654, "initial_base_amount": "3455.8", "remaining_base_amount": "3455.8", "price": "1.97823", "order_expiry": 1775064134581, "transaction_time": 0}, {"order_index": 19421773463719269, "order_id": "19421773463719269", "owner_account_index": 281474976710654, "initial_base_amount": "2962.9", "remaining_base_amount": "2962.9", "price": "1.98018", "order_expiry": 1775064134581, "transaction_time": 0}, {"order_index": 19421773464791423, "order_id": "19421773464791423", "owner_account_index": 102394, "initial_base_amount": "51.1", "remaining_base_amount": "51.1", "price": "1.98194", "order_expiry": 1775184228431, "transaction_time": 0}, {"order_index": 19421773463719270, "order_id": "19421773463719270", "owner_account_index": 281474976710654, "initial_base_amount": "2534.9", "remaining_base_amount": "2534.9", "price": "1.98213", "order_expiry": 1775064134582, "transaction_time": 0}, {"order_index": 19421773463719272, "order_id": "19421773463719272", "owner_account_index": 281474976710654, "initial_base_amount": "2172.3", "remaining_base_amount": "2172.3", "price": "1.98408", "order_expiry": 1775064134582, "transaction_time": 0}, {"order_index": 19421773464211168, "order_id": "19421773464211168", "owner_account_index": 338295, "initial_base_amount": "50.2", "remaining_base_amount": "50.2", "price": "1.98589", "order_expiry": 1774982887548, "transaction_time": 0}, {"order_index": 19421773463719271, "order_id": "19421773463719271", "owner_account_index": 281474976710654, "initial_base_amount": "1867.9", "remaining_base_amount": "1867.9", "price": "1.98603", "order_expiry": 1775064134583, "transaction_time": 0}, {"order_index": 19421773463719273, "order_id": "19421773463719273", "owner_account_index": 281474976710654, "initial_base_amount": "1612.9", "remaining_base_amount": "1612.9", "price": "1.98798", "order_expiry": 1775064134583, "transaction_time": 0}, {"order_index": 19421773463719262, "order_id": "19421773463719262", "owner_account_index": 281474976710654, "initial_base_amount": "133270.8", "remaining_base_amount": "133270.8", "price": "1.98993", "order_expiry": 1775064134566, "transaction_time": 0}, {"order_index": 19421773464791410, "order_id": "19421773464791410", "owner_account_index": 102394, "initial_base_amount": "63.9", "remaining_base_amount": "63.9", "price": "1.99473", "order_expiry": 1775184223632, "transaction_time": 0}, {"order_index": 19421773464190043, "order_id": "19421773464190043", "owner_account_index": 338295, "initial_base_amount": "49.1", "remaining_base_amount": "49.1", "price": "1.99986", "order_expiry": 1774976943304, "transaction_time": 0}, {"order_index": 19421773464263646, "order_id": "19421773464263646", "owner_account_index": 714896, "initial_base_amount": "24.9", "remaining_base_amount": "24.9", "price": "2.00109", "order_expiry": 1774997438955, "transaction_time": 0}, {"order_index": 19421773464190065, "order_id": "19421773464190065", "owner_account_index": 338295, "initial_base_amount": "49.1", "remaining_base_amount": "49.1", "price": "2.01054", "order_expiry": 1774976951321, "transaction_time": 0}, {"order_index": 19421773461937190, "order_id": "19421773461937190", "owner_account_index": 360090, "initial_base_amount": "693.8", "remaining_base_amount": "693.8", "price": "2.01526", "order_expiry": 1774443562316, "transaction_time": 0}, {"order_index": 19421773461892293, "order_id": "19421773461892293", "owner_account_index": 3230, "initial_base_amount": "16.4", "remaining_base_amount": "16.4", "price": "2.01572", "order_expiry": 1774434023663, "transaction_time": 0}, {"order_index": 19421773461892294, "order_id": "19421773461892294", "owner_account_index": 3230, "initial_base_amount": "16.4", "remaining_base_amount": "16.4", "price": "2.02303", "order_expiry": 1774434023663, "transaction_time": 0}, {"order_index": 19421773464190052, "order_id": "19421773464190052", "owner_account_index": 338295, "initial_base_amount": "49.1", "remaining_base_amount": "49.1", "price": "2.02524", "order_expiry": 1774976947724, "transaction_time": 0}, {"order_index": 19421773461937191, "order_id": "19421773461937191", "owner_account_index": 360090, "initial_base_amount": "693.8", "remaining_base_amount": "693.8", "price": "2.02736", "order_expiry": 1774443562316, "transaction_time": 0}, {"order_index": 19421773463611119, "order_id": "19421773463611119", "owner_account_index": 136617, "initial_base_amount": "100.0", "remaining_base_amount": "100.0", "price": "2.02984", "order_expiry": 1774878083405, "transaction_time": 0}, {"order_index": 19421773461892295, "order_id": "19421773461892295", "owner_account_index": 3230, "initial_base_amount": "16.4", "remaining_base_amount": "16.4", "price": "2.03034", "order_expiry": 1774434023663, "transaction_time": 0}, {"order_index": 19421773461892296, "order_id": "19421773461892296", "owner_account_index": 3230, "initial_base_amount": "16.4", "remaining_base_amount": "16.4", "price": "2.03765", "order_expiry": 1774434023663, "transaction_time": 0}, {"order_index": 19421773461892297, "order_id": "19421773461892297", "owner_account_index": 3230, "initial_base_amount": "16.4", "remaining_base_amount": "16.4", "price": "2.04496", "order_expiry": 1774434023663, "transaction_time": 0}, {"order_index": 19421773461892298, "order_id": "19421773461892298", "owner_account_index": 3230, "initial_base_amount": "16.4", "remaining_base_amount": "16.4", "price": "2.05227", "order_expiry": 1774434023663, "transaction_time": 0}, {"order_index": 19421773461892299, "order_id": "19421773461892299", "owner_account_index": 3230, "initial_base_amount": "16.4", "remaining_base_amount": "16.4", "price": "2.05958", "order_expiry": 1774434023663, "transaction_time": 0}, {"order_index": 19421773461892300, "order_id": "19421773461892300", "owner_account_index": 3230, "initial_base_amount": "16.4", "remaining_base_amount": "16.4", "price": "2.06689", "order_expiry": 1774434023663, "transaction_time": 0}, {"order_index": 19421773461892301, "order_id": "19421773461892301", "owner_account_index": 3230, "initial_base_amount": "16.4", "remaining_base_amount": "16.4", "price": "2.07420", "order_expiry": 1774434023663, "transaction_time": 0}, {"order_index": 19421773461892302, "order_id": "19421773461892302", "owner_account_index": 3230, "initial_base_amount": "16.4", "remaining_base_amount": "16.4", "price": "2.08151", "order_expiry": 1774434023663, "transaction_time": 0}, {"order_index": 19421773461892303, "order_id": "19421773461892303", "owner_account_index": 3230, "initial_base_amount": "16.4", "remaining_base_amount": "16.4", "price": "2.08882", "order_expiry": 1774434023663, "transaction_time": 0}, {"order_index": 19421773461892304, "order_id": "19421773461892304", "owner_account_index": 3230, "initial_base_amount": "16.4", "remaining_base_amount": "16.4", "price": "2.09613", "order_expiry": 1774434023663, "transaction_time": 0}, {"order_index": 19421773461892305, "order_id": "19421773461892305", "owner_account_index": 3230, "initial_base_amount": "16.4", "remaining_base_amount": "16.4", "price": "2.10344", "order_expiry": 1774434023663, "transaction_time": 0}, {"order_index": 19421773461892306, "order_id": "19421773461892306", "owner_account_index": 3230, "initial_base_amount": "16.4", "remaining_base_amount": "16.4", "price": "2.11075", "order_expiry": 1774434023663, "transaction_time": 0}, {"order_index": 19421773461892307, "order_id": "19421773461892307", "owner_account_index": 3230, "initial_base_amount": "16.4", "remaining_base_amount": "16.4", "price": "2.11806", "order_expiry": 1774434023663, "transaction_time": 0}, {"order_index": 19421773461892308, "order_id": "19421773461892308", "owner_account_index": 3230, "initial_base_amount": "16.3", "remaining_base_amount": "16.3", "price": "2.12538", "order_expiry": 1774434023663, "transaction_time": 0}, {"order_index": 19421773459790837, "order_id": "19421773459790837", "owner_account_index": 136617, "initial_base_amount": "94.0", "remaining_base_amount": "94.0", "price": "2.12768", "order_expiry": 1773775560888, "transaction_time": 0}], "total_bids": 50, "bids": [{"order_index": 19703248299479647, "order_id": "19703248299479647", "owner_account_index": 281474976710654, "initial_base_amount": "107.9", "remaining_base_amount": "107.6", "price": "1.95144", "order_expiry": 1775354143163, "transaction_time": 0}, {"order_index": 19703248299472585, "order_id": "19703248299472585", "owner_account_index": 281474976649277, "initial_base_amount": "364.8", "remaining_base_amount": "364.8", "price": "1.95096", "order_expiry": 1772851233749, "transaction_time": 0}, {"order_index": 19703248299473297, "order_id": "19703248299473297", "owner_account_index": 281474976648047, "initial_base_amount": "506.2", "remaining_base_amount": "505.0", "price": "1.95058", "order_expiry": 1772850934430, "transaction_time": 0}, {"order_index": 19703248299472207, "order_id": "19703248299472207", "owner_account_index": 281474976648046, "initial_base_amount": "270.2", "remaining_base_amount": "270.2", "price": "1.95041", "order_expiry": 1772851416632, "transaction_time": 0}, {"order_index": 19703248299472276, "order_id": "19703248299472276", "owner_account_index": 68785, "initial_base_amount": "769.3", "remaining_base_amount": "769.3", "price": "1.94974", "order_expiry": 1775184218626, "transaction_time": 0}, {"order_index": 19703248299479632, "order_id": "19703248299479632", "owner_account_index": 281474976710654, "initial_base_amount": "136.3", "remaining_base_amount": "135.8", "price": "1.94948", "order_expiry": 1775354150486, "transaction_time": 0}, {"order_index": 19703248299479594, "order_id": "19703248299479594", "owner_account_index": 281474976710654, "initial_base_amount": "170.0", "remaining_base_amount": "169.5", "price": "1.94899", "order_expiry": 1775354160010, "transaction_time": 0}, {"order_index": 19703248299472237, "order_id": "19703248299472237", "owner_account_index": 366058, "initial_base_amount": "1535.7", "remaining_base_amount": "1535.7", "price": "1.94890", "order_expiry": 1772766824455, "transaction_time": 0}, {"order_index": 19703248299472281, "order_id": "19703248299472281", "owner_account_index": 102394, "initial_base_amount": "146.6", "remaining_base_amount": "146.6", "price": "1.94611", "order_expiry": 1775184218321, "transaction_time": 0}, {"order_index": 19703248299472317, "order_id": "19703248299472317", "owner_account_index": 102394, "initial_base_amount": "319.7", "remaining_base_amount": "319.7", "price": "1.94344", "order_expiry": 1775184199231, "transaction_time": 0}, {"order_index": 19703248299472231, "order_id": "19703248299472231", "owner_account_index": 102394, "initial_base_amount": "168.3", "remaining_base_amount": "168.3", "price": "1.94200", "order_expiry": 1775184231062, "transaction_time": 0}, {"order_index": 19703248299472201, "order_id": "19703248299472201", "owner_account_index": 102394, "initial_base_amount": "383.3", "remaining_base_amount": "383.3", "price": "1.94118", "order_expiry": 1775184242834, "transaction_time": 0}, {"order_index": 19703248299472314, "order_id": "19703248299472314", "owner_account_index": 102394, "initial_base_amount": "767.4", "remaining_base_amount": "767.4", "price": "1.93062", "order_expiry": 1775184204029, "transaction_time": 0}, {"order_index": 19703248299478164, "order_id": "19703248299478164", "owner_account_index": 281474976710654, "initial_base_amount": "2450.5", "remaining_base_amount": "2450.5", "price": "1.92962", "order_expiry": 1775354702892, "transaction_time": 0}, {"order_index": 19703248299478163, "order_id": "19703248299478163", "owner_account_index": 281474976710654, "initial_base_amount": "3489.8", "remaining_base_amount": "3489.8", "price": "1.92767", "order_expiry": 1775354702893, "transaction_time": 0}, {"order_index": 19703248299478162, "order_id": "19703248299478162", "owner_account_index": 281474976710654, "initial_base_amount": "3434.8", "remaining_base_amount": "3434.8", "price": "1.92573", "order_expiry": 1775354702893, "transaction_time": 0}, {"order_index": 19703248299478161, "order_id": "19703248299478161", "owner_account_index": 281474976710654, "initial_base_amount": "3074.0", "remaining_base_amount": "3074.0", "price": "1.92378", "order_expiry": 1775354702894, "transaction_time": 0}, {"order_index": 19703248300514350, "order_id": "19703248300514350", "owner_account_index": 281474976710654, "initial_base_amount": "3247.6", "remaining_base_amount": "2664.2", "price": "1.92183", "order_expiry": 1775064134571, "transaction_time": 0}, {"order_index": 19703248300514349, "order_id": "19703248300514349", "owner_account_index": 281474976710654, "initial_base_amount": "2284.2", "remaining_base_amount": "2284.2", "price": "1.91988", "order_expiry": 1775064134572, "transaction_time": 0}, {"order_index": 19703248299472230, "order_id": "19703248299472230", "owner_account_index": 102394, "initial_base_amount": "51.1", "remaining_base_amount": "51.1", "price": "1.91938", "order_expiry": 1775184233231, "transaction_time": 0}, {"order_index": 19703248300514348, "order_id": "19703248300514348", "owner_account_index": 281474976710654, "initial_base_amount": "1954.3", "remaining_base_amount": "1954.3", "price": "1.91793", "order_expiry": 1775064134572, "transaction_time": 0}, {"order_index": 19703248300514346, "order_id": "19703248300514346", "owner_account_index": 281474976710654, "initial_base_amount": "1674.7", "remaining_base_amount": "1674.7", "price": "1.91598", "order_expiry": 1775064134573, "transaction_time": 0}, {"order_index": 19703248300514347, "order_id": "19703248300514347", "owner_account_index": 281474976710654, "initial_base_amount": "1440.1", "remaining_base_amount": "1440.1", "price": "1.91403", "order_expiry": 1775064134573, "transaction_time": 0}, {"order_index": 19703248300514345, "order_id": "19703248300514345", "owner_account_index": 281474976710654, "initial_base_amount": "1243.5", "remaining_base_amount": "1243.5", "price": "1.91208", "order_expiry": 1775064134574, "transaction_time": 0}, {"order_index": 19703248300514355, "order_id": "19703248300514355", "owner_account_index": 281474976710654, "initial_base_amount": "127555.7", "remaining_base_amount": "127555.7", "price": "1.91013", "order_expiry": 1775064134565, "transaction_time": 0}, {"order_index": 19703248299472224, "order_id": "19703248299472224", "owner_account_index": 102394, "initial_base_amount": "63.8", "remaining_base_amount": "63.8", "price": "1.90677", "order_expiry": 1775184238033, "transaction_time": 0}, {"order_index": 19703248299513029, "order_id": "19703248299513029", "owner_account_index": 98666, "initial_base_amount": "7.8", "remaining_base_amount": "7.8", "price": "1.89978", "order_expiry": 1775168291467, "transaction_time": 0}, {"order_index": 19703248299665842, "order_id": "19703248299665842", "owner_account_index": 59229, "initial_base_amount": "117.2", "remaining_base_amount": "117.2", "price": "1.89492", "order_expiry": 1775120176690, "transaction_time": 0}, {"order_index": 19703248300136688, "order_id": "19703248300136688", "owner_account_index": 360090, "initial_base_amount": "9234.9", "remaining_base_amount": "9234.9", "price": "1.67047", "order_expiry": 1774966143568, "transaction_time": 0}, {"order_index": 19703248299566043, "order_id": "19703248299566043", "owner_account_index": 2751, "initial_base_amount": "13999.4", "remaining_base_amount": "13999.4", "price": "1.66680", "order_expiry": 1775150194539, "transaction_time": 0}, {"order_index": 19703248301257599, "order_id": "19703248301257599", "owner_account_index": 360090, "initial_base_amount": "8863.3", "remaining_base_amount": "8863.3", "price": "1.53627", "order_expiry": 1774668510423, "transaction_time": 0}, {"order_index": 19703248301384493, "order_id": "19703248301384493", "owner_account_index": 3230, "initial_base_amount": "47.2", "remaining_base_amount": "47.2", "price": "1.52000", "order_expiry": 1774623941138, "transaction_time": 0}, {"order_index": 19703248301384492, "order_id": "19703248301384492", "owner_account_index": 3230, "initial_base_amount": "47.2", "remaining_base_amount": "47.2", "price": "1.51586", "order_expiry": 1774623941138, "transaction_time": 0}, {"order_index": 19703248301384491, "order_id": "19703248301384491", "owner_account_index": 3230, "initial_base_amount": "47.2", "remaining_base_amount": "47.2", "price": "1.51172", "order_expiry": 1774623941138, "transaction_time": 0}, {"order_index": 19703248301384490, "order_id": "19703248301384490", "owner_account_index": 3230, "initial_base_amount": "47.2", "remaining_base_amount": "47.2", "price": "1.50758", "order_expiry": 1774623941138, "transaction_time": 0}, {"order_index": 19703248301384489, "order_id": "19703248301384489", "owner_account_index": 3230, "initial_base_amount": "47.2", "remaining_base_amount": "47.2", "price": "1.50344", "order_expiry": 1774623941138, "transaction_time": 0}, {"order_index": 19703248302987223, "order_id": "19703248302987223", "owner_account_index": 62258, "initial_base_amount": "66.7", "remaining_base_amount": "66.7", "price": "1.50000", "order_expiry": 1774143726571, "transaction_time": 0}, {"order_index": 19703248301384488, "order_id": "19703248301384488", "owner_account_index": 3230, "initial_base_amount": "47.2", "remaining_base_amount": "47.2", "price": "1.49931", "order_expiry": 1774623941138, "transaction_time": 0}, {"order_index": 19703248301384487, "order_id": "19703248301384487", "owner_account_index": 3230, "initial_base_amount": "47.2", "remaining_base_amount": "47.2", "price": "1.49517", "order_expiry": 1774623941138, "transaction_time": 0}, {"order_index": 19703248301384486, "order_id": "19703248301384486", "owner_account_index": 3230, "initial_base_amount": "47.2", "remaining_base_amount": "47.2", "price": "1.49103", "order_expiry": 1774623941138, "transaction_time": 0}, {"order_index": 19703248303218228, "order_id": "19703248303218228", "owner_account_index": 2192, "initial_base_amount": "300.0", "remaining_base_amount": "300.0", "price": "1.49000", "order_expiry": 1774056713466, "transaction_time": 0}, {"order_index": 19703248301384485, "order_id": "19703248301384485", "owner_account_index": 3230, "initial_base_amount": "47.2", "remaining_base_amount": "47.2", "price": "1.48689", "order_expiry": 1774623941138, "transaction_time": 0}, {"order_index": 19703248301384484, "order_id": "19703248301384484", "owner_account_index": 3230, "initial_base_amount": "47.2", "remaining_base_amount": "47.2", "price": "1.48275", "order_expiry": 1774623941138, "transaction_time": 0}, {"order_index": 19703248301384483, "order_id": "19703248301384483", "owner_account_index": 3230, "initial_base_amount": "47.2", "remaining_base_amount": "47.2", "price": "1.47862", "order_expiry": 1774623941138, "transaction_time": 0}, {"order_index": 19703248301384482, "order_id": "19703248301384482", "owner_account_index": 3230, "initial_base_amount": "47.2", "remaining_base_amount": "47.2", "price": "1.47448", "order_expiry": 1774623941138, "transaction_time": 0}, {"order_index": 19703248301384481, "order_id": "19703248301384481", "owner_account_index": 3230, "initial_base_amount": "47.2", "remaining_base_amount": "47.2", "price": "1.47034", "order_expiry": 1774623941138, "transaction_time": 0}, {"order_index": 19703248301384480, "order_id": "19703248301384480", "owner_account_index": 3230, "initial_base_amount": "47.2", "remaining_base_amount": "47.2", "price": "1.46620", "order_expiry": 1774623941138, "transaction_time": 0}, {"order_index": 19703248301384479, "order_id": "19703248301384479", "owner_account_index": 3230, "initial_base_amount": "47.2", "remaining_base_amount": "47.2", "price": "1.46206", "order_expiry": 1774623941138, "transaction_time": 0}, {"order_index": 19703248301384478, "order_id": "19703248301384478", "owner_account_index": 3230, "initial_base_amount": "47.2", "remaining_base_amount": "47.2", "price": "1.45793", "order_expiry": 1774623941138, "transaction_time": 0}, {"order_index": 19703248301384477, "order_id": "19703248301384477", "owner_account_index": 3230, "initial_base_amount": "47.2", "remaining_base_amount": "47.2", "price": "1.45379", "order_expiry": 1774623941138, "transaction_time": 0}]}