{"code": 200, "total_asks": 50, "asks": [{"order_index": 23925373086973518, "order_id": "23925373086973518", "owner_account_index": 317087, "initial_base_amount": "2000.87", "remaining_base_amount": "2000.87", "price": "0.6219", "order_expiry": 1775212271481, "transaction_time": 0}, {"order_index": 23925373086973470, "order_id": "23925373086973470", "owner_account_index": 317087, "initial_base_amount": "2981.90", "remaining_base_amount": "2981.90", "price": "0.6220", "order_expiry": 1775212248272, "transaction_time": 0}, {"order_index": 23925373086829102, "order_id": "23925373086829102", "owner_account_index": 281474976710654, "initial_base_amount": "3985.29", "remaining_base_amount": "3884.70", "price": "0.6222", "order_expiry": 1775298753972, "transaction_time": 0}, {"order_index": 23925373086829746, "order_id": "23925373086829746", "owner_account_index": 281474976710654, "initial_base_amount": "4856.60", "remaining_base_amount": "4856.55", "price": "0.6223", "order_expiry": 1775298994272, "transaction_time": 0}, {"order_index": 23925373086829684, "order_id": "23925373086829684", "owner_account_index": 281474976710654, "initial_base_amount": "6061.02", "remaining_base_amount": "6060.98", "price": "0.6225", "order_expiry": 1775298993373, "transaction_time": 0}, {"order_index": 23925373086973519, "order_id": "23925373086973519", "owner_account_index": 366058, "initial_base_amount": "1608.63", "remaining_base_amount": "1608.63", "price": "0.6227", "order_expiry": 1772794871539, "transaction_time": 0}, {"order_index": 23925373086973430, "order_id": "23925373086973430", "owner_account_index": 314233, "initial_base_amount": "2250.61", "remaining_base_amount": "2250.61", "price": "0.6233", "order_expiry": 1775212229672, "transaction_time": 0}, {"order_index": 23925373086973437, "order_id": "23925373086973437", "owner_account_index": 317087, "initial_base_amount": "19879.35", "remaining_base_amount": "19879.35", "price": "0.6234", "order_expiry": 1775212231060, "transaction_time": 0}, {"order_index": 23925373086973444, "order_id": "23925373086973444", "owner_account_index": 314233, "initial_base_amount": "9002.43", "remaining_base_amount": "9002.43", "price": "0.6251", "order_expiry": 1775212233641, "transaction_time": 0}, {"order_index": 23925373086973469, "order_id": "23925373086973469", "owner_account_index": 317087, "initial_base_amount": "74547.55", "remaining_base_amount": "74547.55", "price": "0.6280", "order_expiry": 1775212248270, "transaction_time": 0}, {"order_index": 23925373086361547, "order_id": "23925373086361547", "owner_account_index": 281474976710654, "initial_base_amount": "20668.38", "remaining_base_amount": "20668.38", "price": "0.6291", "order_expiry": 1775064134558, "transaction_time": 0}, {"order_index": 23925373086361548, "order_id": "23925373086361548", "owner_account_index": 281474976710654, "initial_base_amount": "29434.87", "remaining_base_amount": "29434.87", "price": "0.6297", "order_expiry": 1775064134558, "transaction_time": 0}, {"order_index": 23925373086361549, "order_id": "23925373086361549", "owner_account_index": 281474976710654, "initial_base_amount": "28970.67", "remaining_base_amount": "28970.67", "price": "0.6304", "order_expiry": 1775064134559, "transaction_time": 0}, {"order_index": 23925373086973432, "order_id": "23925373086973432", "owner_account_index": 314233, "initial_base_amount": "21738.57", "remaining_base_amount": "21738.57", "price": "0.6306", "order_expiry": 1775212229791, "transaction_time": 0}, {"order_index": 23925373086361550, "order_id": "23925373086361550", "owner_account_index": 281474976710654, "initial_base_amount": "25927.46", "remaining_base_amount": "25927.46", "price": "0.6310", "order_expiry": 1775064134559, "transaction_time": 0}, {"order_index": 23925373086361551, "order_id": "23925373086361551", "owner_account_index": 281474976710654, "initial_base_amount": "22470.98", "remaining_base_amount": "22470.98", "price": "0.6316", "order_expiry": 1775064134560, "transaction_time": 0}, {"order_index": 23925373086361552, "order_id": "23925373086361552", "owner_account_index": 281474976710654, "initial_base_amount": "19266.34", "remaining_base_amount": "19266.34", "price": "0.6322", "order_expiry": 1775064134560, "transaction_time": 0}, {"order_index": 23925373086361555, "order_id": "23925373086361555", "owner_account_index": 281474976710654, "initial_base_amount": "16483.08", "remaining_base_amount": "16483.08", "price": "0.6329", "order_expiry": 1775064134561, "transaction_time": 0}, {"order_index": 23925373086361553, "order_id": "23925373086361553", "owner_account_index": 281474976710654, "initial_base_amount": "14125.36", "remaining_base_amount": "14125.36", "price": "0.6335", "order_expiry": 1775064134561, "transaction_time": 0}, {"order_index": 23925373086361554, "order_id": "23925373086361554", "owner_account_index": 281474976710654, "initial_base_amount": "12146.17", "remaining_base_amount": "12146.17", "price": "0.6341", "order_expiry": 1775064134562, "transaction_time": 0}, {"order_index": 23925373086361556, "order_id": "23925373086361556", "owner_account_index": 281474976710654, "initial_base_amount": "10487.91", "remaining_base_amount": "10487.91", "price": "0.6347", "order_expiry": 1775064134562, "transaction_time": 0}, {"order_index": 23925373086973419, "order_id": "23925373086973419", "owner_account_index": 314233, "initial_base_amount": "32523.13", "remaining_base_amount": "32523.13", "price": "0.6388", "order_expiry": 1775212225474, "transaction_time": 0}, {"order_index": 23925373086361543, "order_id": "23925373086361543", "owner_account_index": 281474976710654, "initial_base_amount": "278779.29", "remaining_base_amount": "278779.29", "price": "0.6416", "order_expiry": 1775064134525, "transaction_time": 0}, {"order_index": 23925373086973492, "order_id": "23925373086973492", "owner_account_index": 314233, "initial_base_amount": "43484.11", "remaining_base_amount": "43484.11", "price": "0.6486", "order_expiry": 1775212260180, "transaction_time": 0}, {"order_index": 23925373084522191, "order_id": "23925373084522191", "owner_account_index": 41575, "initial_base_amount": "35.79", "remaining_base_amount": "35.79", "price": "0.8431", "order_expiry": 1774075503997, "transaction_time": 0}, {"order_index": 23925373086126121, "order_id": "23925373086126121", "owner_account_index": 89532, "initial_base_amount": "1000.00", "remaining_base_amount": "1000.00", "price": "0.8760", "order_expiry": 1774778147603, "transaction_time": 0}, {"order_index": 23925373086123415, "order_id": "23925373086123415", "owner_account_index": 89532, "initial_base_amount": "2000.00", "remaining_base_amount": "2000.00", "price": "0.8960", "order_expiry": 1774776826152, "transaction_time": 0}, {"order_index": 23925373086692399, "order_id": "23925373086692399", "owner_account_index": 253636, "initial_base_amount": "800.00", "remaining_base_amount": "800.00", "price": "0.9184", "order_expiry": 1775053509170, "transaction_time": 0}, {"order_index": 23925373086125799, "order_id": "23925373086125799", "owner_account_index": 89532, "initial_base_amount": "700.00", "remaining_base_amount": "700.00", "price": "0.9780", "order_expiry": 1774777971221, "transaction_time": 0}, {"order_index": 23925373086125804, "order_id": "23925373086125804", "owner_account_index": 89532, "initial_base_amount": "700.00", "remaining_base_amount": "700.00", "price": "1.0080", "order_expiry": 1774777977051, "transaction_time": 0}, {"order_index": 23925373086125824, "order_id": "23925373086125824", "owner_account_index": 89532, "initial_base_amount": "700.00", "remaining_base_amount": "700.00", "price": "1.0380", "order_expiry": 1774777981995, "transaction_time": 0}, {"order_index": 23925373086961124, "order_id": "23925373086961124", "owner_account_index": 41575, "initial_base_amount": "40.27", "remaining_base_amount": "40.27", "price": "1.0416", "order_expiry": 1775204513293, "transaction_time": 0}, {"order_index": 23925373086125832, "order_id": "23925373086125832", "owner_account_index": 89532, "initial_base_amount": "700.00", "remaining_base_amount": "700.00", "price": "1.0680", "order_expiry": 1774777986548, "transaction_time": 0}, {"order_index": 23925373086125841, "order_id": "23925373086125841", "owner_account_index": 89532, "initial_base_amount": "700.00", "remaining_base_amount": "700.00", "price": "1.0980", "order_expiry": 1774777993570, "transaction_time": 0}, {"order_index": 23925373086125872, "order_id": "23925373086125872", "owner_account_index": 89532, "initial_base_amount": "700.00", "remaining_base_amount": "700.00", "price": "1.1280", "order_expiry": 1774778007430, "transaction_time": 0}, {"order_index": 23925373086467103, "order_id": "23925373086467103", "owner_account_index": 41575, "initial_base_amount": "32.68", "remaining_base_amount": "32.68", "price": "1.1493", "order_expiry": 1774949250045, "transaction_time": 0}, {"order_index": 23925373086125878, "order_id": "23925373086125878", "owner_account_index": 89532, "initial_base_amount": "700.00", "remaining_base_amount": "700.00", "price": "1.1580", "order_expiry": 1774778011178, "transaction_time": 0}, {"order_index": 23925373086125899, "order_id": "23925373086125899", "owner_account_index": 89532, "initial_base_amount": "700.00", "remaining_base_amount": "700.00", "price": "1.1880", "order_expiry": 1774778015271, "transaction_time": 0}, {"order_index": 23925373086125912, "order_id": "23925373086125912", "owner_account_index": 89532, "initial_base_amount": "700.00", "remaining_base_amount": "700.00", "price": "1.2180", "order_expiry": 1774778022587, "transaction_time": 0}, {"order_index": 23925373084729361, "order_id": "23925373084729361", "owner_account_index": 41575, "initial_base_amount": "25.36", "remaining_base_amount": "25.36", "price": "1.2187", "order_expiry": 1774171854825, "transaction_time": 0}, {"order_index": 23925373086125929, "order_id": "23925373086125929", "owner_account_index": 89532, "initial_base_amount": "700.00", "remaining_base_amount": "700.00", "price": "1.2480", "order_expiry": 1774778026257, "transaction_time": 0}, {"order_index": 23925373086125942, "order_id": "23925373086125942", "owner_account_index": 89532, "initial_base_amount": "700.00", "remaining_base_amount": "700.00", "price": "1.2780", "order_expiry": 1774778030264, "transaction_time": 0}, {"order_index": 23925373083244241, "order_id": "23925373083244241", "owner_account_index": 41575, "initial_base_amount": "24.80", "remaining_base_amount": "24.80", "price": "1.2878", "order_expiry": 1773650481830, "transaction_time": 0}, {"order_index": 23925373086125953, "order_id": "23925373086125953", "owner_account_index": 89532, "initial_base_amount": "700.00", "remaining_base_amount": "700.00", "price": "1.3080", "order_expiry": 1774778035913, "transaction_time": 0}, {"order_index": 23925373086125957, "order_id": "23925373086125957", "owner_account_index": 89532, "initial_base_amount": "700.00", "remaining_base_amount": "700.00", "price": "1.3380", "order_expiry": 1774778039451, "transaction_time": 0}, {"order_index": 23925373086125969, "order_id": "23925373086125969", "owner_account_index": 89532, "initial_base_amount": "700.00", "remaining_base_amount": "700.00", "price": "1.3680", "order_expiry": 1774778047413, "transaction_time": 0}, {"order_index": 23925373086125975, "order_id": "23925373086125975", "owner_account_index": 89532, "initial_base_amount": "700.00", "remaining_base_amount": "700.00", "price": "1.3980", "order_expiry": 1774778051632, "transaction_time": 0}, {"order_index": 23925373086125983, "order_id": "23925373086125983", "owner_account_index": 89532, "initial_base_amount": "700.00", "remaining_base_amount": "700.00", "price": "1.4280", "order_expiry": 1774778058418, "transaction_time": 0}, {"order_index": 23925373083417457, "order_id": "23925373083417457", "owner_account_index": 41575, "initial_base_amount": "17.52", "remaining_base_amount": "17.52", "price": "1.7022", "order_expiry": 1773732328250, "transaction_time": 0}, {"order_index": 23925373085538101, "order_id": "23925373085538101", "owner_account_index": 41575, "initial_base_amount": "6.01", "remaining_base_amount": "6.01", "price": "1.8175", "order_expiry": 1774523026698, "transaction_time": 0}], "total_bids": 29, "bids": [{"order_index": 24206847934805208, "order_id": "24206847934805208", "owner_account_index": 281474976710654, "initial_base_amount": "10343.03", "remaining_base_amount": "6336.62", "price": "0.6213", "order_expiry": 1775359791478, "transaction_time": 0}, {"order_index": 24206847934764798, "order_id": "24206847934764798", "owner_account_index": 317087, "initial_base_amount": "2053.36", "remaining_base_amount": "2053.27", "price": "0.6212", "order_expiry": 1775212287261, "transaction_time": 0}, {"order_index": 24206847934798253, "order_id": "24206847934798253", "owner_account_index": 281474976710654, "initial_base_amount": "7925.82", "remaining_base_amount": "7925.81", "price": "0.6208", "order_expiry": 1775364357661, "transaction_time": 0}, {"order_index": 24206847934805188, "order_id": "24206847934805188", "owner_account_index": 281474976710654, "initial_base_amount": "9891.52", "remaining_base_amount": "9891.41", "price": "0.6206", "order_expiry": 1775359800606, "transaction_time": 0}, {"order_index": 24206847934764900, "order_id": "24206847934764900", "owner_account_index": 317087, "initial_base_amount": "3023.77", "remaining_base_amount": "3023.77", "price": "0.6205", "order_expiry": 1775212233901, "transaction_time": 0}, {"order_index": 24206847934764813, "order_id": "24206847934764813", "owner_account_index": 366058, "initial_base_amount": "1609.73", "remaining_base_amount": "1609.73", "price": "0.6201", "order_expiry": 1772794872867, "transaction_time": 0}, {"order_index": 24206847934764910, "order_id": "24206847934764910", "owner_account_index": 314233, "initial_base_amount": "2187.99", "remaining_base_amount": "2187.99", "price": "0.6191", "order_expiry": 1775212230978, "transaction_time": 0}, {"order_index": 24206847934764876, "order_id": "24206847934764876", "owner_account_index": 317087, "initial_base_amount": "20533.60", "remaining_base_amount": "20533.60", "price": "0.6190", "order_expiry": 1775212248276, "transaction_time": 0}, {"order_index": 24206847934764850, "order_id": "24206847934764850", "owner_account_index": 314233, "initial_base_amount": "9085.73", "remaining_base_amount": "9085.73", "price": "0.6166", "order_expiry": 1775212260271, "transaction_time": 0}, {"order_index": 24206847935387464, "order_id": "24206847935387464", "owner_account_index": 281474976710654, "initial_base_amount": "22414.70", "remaining_base_amount": "22414.70", "price": "0.6162", "order_expiry": 1775064134528, "transaction_time": 0}, {"order_index": 24206847935387468, "order_id": "24206847935387468", "owner_account_index": 281474976710654, "initial_base_amount": "31921.90", "remaining_base_amount": "31921.90", "price": "0.6156", "order_expiry": 1775064134528, "transaction_time": 0}, {"order_index": 24206847935387465, "order_id": "24206847935387465", "owner_account_index": 281474976710654, "initial_base_amount": "31418.48", "remaining_base_amount": "31418.48", "price": "0.6150", "order_expiry": 1775064134529, "transaction_time": 0}, {"order_index": 24206847935387466, "order_id": "24206847935387466", "owner_account_index": 281474976710654, "initial_base_amount": "28118.13", "remaining_base_amount": "28118.13", "price": "0.6144", "order_expiry": 1775064134529, "transaction_time": 0}, {"order_index": 24206847934764877, "order_id": "24206847934764877", "owner_account_index": 317087, "initial_base_amount": "77001.01", "remaining_base_amount": "77001.01", "price": "0.6140", "order_expiry": 1775212248274, "transaction_time": 0}, {"order_index": 24206847935387469, "order_id": "24206847935387469", "owner_account_index": 281474976710654, "initial_base_amount": "24369.61", "remaining_base_amount": "24369.61", "price": "0.6138", "order_expiry": 1775064134530, "transaction_time": 0}, {"order_index": 24206847935387467, "order_id": "24206847935387467", "owner_account_index": 281474976710654, "initial_base_amount": "20894.20", "remaining_base_amount": "20894.20", "price": "0.6131", "order_expiry": 1775064134530, "transaction_time": 0}, {"order_index": 24206847935387463, "order_id": "24206847935387463", "owner_account_index": 281474976710654, "initial_base_amount": "17875.77", "remaining_base_amount": "17875.77", "price": "0.6125", "order_expiry": 1775064134531, "transaction_time": 0}, {"order_index": 24206847934764926, "order_id": "24206847934764926", "owner_account_index": 314233, "initial_base_amount": "22714.33", "remaining_base_amount": "22714.33", "price": "0.6120", "order_expiry": 1775212226359, "transaction_time": 0}, {"order_index": 24206847935387460, "order_id": "24206847935387460", "owner_account_index": 281474976710654, "initial_base_amount": "15318.85", "remaining_base_amount": "15318.85", "price": "0.6119", "order_expiry": 1775064134531, "transaction_time": 0}, {"order_index": 24206847935387462, "order_id": "24206847935387462", "owner_account_index": 281474976710654, "initial_base_amount": "13172.43", "remaining_base_amount": "13172.43", "price": "0.6113", "order_expiry": 1775064134542, "transaction_time": 0}, {"order_index": 24206847935387461, "order_id": "24206847935387461", "owner_account_index": 281474976710654, "initial_base_amount": "11374.06", "remaining_base_amount": "11374.06", "price": "0.6106", "order_expiry": 1775064134542, "transaction_time": 0}, {"order_index": 24206847934765953, "order_id": "24206847934765953", "owner_account_index": 314233, "initial_base_amount": "33492.61", "remaining_base_amount": "33492.61", "price": "0.6045", "order_expiry": 1775211534915, "transaction_time": 0}, {"order_index": 24206847935387471, "order_id": "24206847935387471", "owner_account_index": 281474976710654, "initial_base_amount": "281138.31", "remaining_base_amount": "281138.31", "price": "0.6038", "order_expiry": 1775064134524, "transaction_time": 0}, {"order_index": 24206847934765973, "order_id": "24206847934765973", "owner_account_index": 314233, "initial_base_amount": "44777.98", "remaining_base_amount": "44777.98", "price": "0.5942", "order_expiry": 1775211528463, "transaction_time": 0}, {"order_index": 24206847935607882, "order_id": "24206847935607882", "owner_account_index": 23052, "initial_base_amount": "145.81", "remaining_base_amount": "145.81", "price": "0.5704", "order_expiry": 1774781985484, "transaction_time": 0}, {"order_index": 24206847935617387, "order_id": "24206847935617387", "owner_account_index": 89532, "initial_base_amount": "2000.00", "remaining_base_amount": "2000.00", "price": "0.5020", "order_expiry": 1774776811302, "transaction_time": 0}, {"order_index": 24206847935617405, "order_id": "24206847935617405", "owner_account_index": 89532, "initial_base_amount": "2100.00", "remaining_base_amount": "2100.00", "price": "0.4860", "order_expiry": 1774776798883, "transaction_time": 0}, {"order_index": 24206847935617414, "order_id": "24206847935617414", "owner_account_index": 89532, "initial_base_amount": "2200.00", "remaining_base_amount": "2200.00", "price": "0.4560", "order_expiry": 1774776790068, "transaction_time": 0}, {"order_index": 24206847937638468, "order_id": "24206847937638468", "owner_account_index": 703163, "initial_base_amount": "24.44", "remaining_base_amount": "24.44", "price": "0.4500", "order_expiry": 1773979749570, "transaction_time": 0}]}